gutsygit/__init__.py
gutsygit/client.py
gutsygit/main.py
gutsygit/utils.py
gutsygit-0.6.0.dist-info/entry_points.txt
gutsygit-0.6.0.dist-info/LICENSE
gutsygit-0.6.0.dist-info/WHEEL
gutsygit-0.6.0.dist-info/METADATA
gutsygit-0.6.0.dist-info/RECORD
