Metadata-Version: 2.1
Name: gutsygit
Version: 0.6.0
Summary: Command-line tool for fast git usage
Home-page: http://github.com/sanderland/gutsygit
License: Apache-2.0
Keywords: git,productivity
Author: Sander Land
Requires-Python: >=3.7,<4.0
Classifier: License :: OSI Approved :: Apache Software License
Classifier: Programming Language :: Python :: 3
Classifier: Programming Language :: Python :: 3.7
Classifier: Programming Language :: Python :: 3.8
Classifier: Programming Language :: Python :: 3.9
Requires-Dist: GitPython (>=3)
Requires-Dist: colorama (>=0.4.4,<0.5.0)
Project-URL: Repository, http://github.com/sanderland/gutsygit
